{
  "info": {
    "key": "g1095_0117"
  },
  "sheets": {
    "מזומנים": {
      "columns": [
        "שם המנפיק/שם נייר ערך",
        "מספר ני\"ע",
        "מספר מנפיק",
        "דירוג",
        "שם מדרג",
        "סוג מטבע",
        "שיעור ריבית",
        "תשואה לפידיון",
        "שווי שוק",
        "שעור מנכסי אפיק ההשקעה",
        "שעור מסך נכסי השקעה"
      ],
      "data": [
        [
          "עו'ש- לאומי",
          "1111111111- 10",
          10,
          "AAA",
          "מעלות",
          "שקל חדש",
          0,
          0,
          64.38245,
          69.32,
          0.12
        ],
        [
          "דולר- לאומי",
          "20001- 10",
          10,
          "AAA",
          "מעלות",
          "דולר אמריקאי",
          0,
          0,
          28.4961051,
          30.68,
          0.06
        ]
      ]
    },
    "תעודות התחייבות ממשלתיות": {
      "columns": [
        "שם המנפיק/שם נייר ערך",
        "מספר ני\"ע",
        "זירת מסחר",
        "דירוג",
        "שם מדרג",
        "תאריך רכישה",
        "מח\"מ",
        "סוג מטבע",
        "שיעור ריבית",
        "תשואה לפידיון",
        "ערך נקוב",
        "שער",
        "שווי שוק",
        "שעור מערך נקוב מונפק",
        "שעור מנכסי אפיק ההשקעה",
        "שעור מסך נכסי השקעה"
      ],
      "data": [
        [
          "גליל 5903- גליל",
          9590332,
          "TASE",
          "RF",
          "פנימי",
          "09/03/17",
          4.0,
          "שקל חדש",
          4.0,
          0.0,
          725000,
          154.38,
          1119.255,
          0.0,
          4.2,
          2.17
        ],
        [
          "גליל 5904- גליל",
          9590431,
          "TASE",
          "RF",
          "פנימי",
          "19/03/17",
          6.47,
          "שקל חדש",
          4.0,
          0.0,
          100000,
          156.35,
          156.35,
          0.0,
          0.59,
          0.3
        ],
        [
          "ממשל צמודה 0418- גליל",
          1108927,
          "TASE",
          "RF",
          "פנימי",
          "18/02/16",
          1.05,
          "שקל חדש",
          3.5,
          0.0,
          2250000,
          123.76,
          2784.6,
          0.01,
          10.45,
          5.4
        ],
        [
          "ממשל צמודה 0923- גליל",
          1128081,
          "TASE",
          "RF",
          "פנימי",
          "09/03/17",
          6.17,
          "שקל חדש",
          1.75,
          0.0,
          4240000,
          110.29,
          4676.296,
          0.03,
          17.55,
          9.08
        ],
        [
          "ממשלתי צמוד 1020- גליל",
          1137181,
          "TASE",
          "RF",
          "פנימי",
          "10/10/16",
          3.58,
          "שקל חדש",
          0.1,
          0.0,
          300000,
          100.0,
          300.0,
          0.0,
          1.13,
          0.58
        ],
        [
          "ממשלתי צמודה 922- גליל",
          1124056,
          "TASE",
          "RF",
          "פנימי",
          "15/08/16",
          5.15,
          "שקל חדש",
          2.75,
          0.0,
          3925000,
          118.22,
          4640.135,
          0.02,
          17.41,
          9.01
        ],
        [
          "ממשלתית צמודה 517- גליל",
          1125905,
          "TASE",
          "RF",
          "פנימי",
          "02/11/15",
          0.16,
          "שקל חדש",
          1.0,
          -0.01,
          1325000,
          102.98,
          1364.485,
          0.02,
          5.12,
          2.65
        ],
        [
          "ממשל שקלית 0219- שחר",
          1110907,
          "TASE",
          "RF",
          "פנימי",
          "24/09/15",
          1.86,
          "שקל חדש",
          6.0,
          0.0,
          2000000,
          111.37,
          2227.4,
          0.01,
          8.36,
          4.32
        ],
        [
          "ממשל שקלית 0825- שחר",
          1135557,
          "TASE",
          "RF",
          "פנימי",
          "27/10/16",
          7.82,
          "שקל חדש",
          1.75,
          0.02,
          250000,
          99.75,
          249.375,
          0.0,
          0.94,
          0.48
        ],
        [
          "ממשל שקלית 120- שחר",
          1115773,
          "TASE",
          "RF",
          "פנימי",
          "04/02/16",
          2.71,
          "שקל חדש",
          5.0,
          0.01,
          1900000,
          113.37,
          2154.03,
          0.01,
          8.08,
          4.18
        ],
        [
          "ממשל שקלית 421- שחר",
          1138130,
          "TASE",
          "RF",
          "פנימי",
          "19/04/16",
          3.99,
          "שקל חדש",
          1.0,
          0.01,
          3745000,
          101.46,
          3799.677,
          0.04,
          14.26,
          7.38
        ],
        [
          "ממשל שקלית 519- שחר",
          1131770,
          "TASE",
          "RF",
          "פנימי",
          "05/02/15",
          2.1,
          "שקל חדש",
          2.25,
          0.0,
          220000,
          105.88,
          232.936,
          0.0,
          0.87,
          0.45
        ],
        [
          "ממשלתי שקלי  1026- שחר",
          1099456,
          "TASE",
          "RF",
          "פנימי",
          "19/10/16",
          7.69,
          "שקל חדש",
          6.25,
          0.02,
          800000,
          139.28,
          1114.24,
          0.0,
          4.18,
          2.16
        ],
        [
          "ממשלתי שקלי 324- שחר",
          1130848,
          "TASE",
          "RF",
          "פנימי",
          "01/12/16",
          6.34,
          "שקל חדש",
          3.75,
          0.02,
          200000,
          114.3,
          228.6,
          0.0,
          0.86,
          0.44
        ],
        [
          "ממשלתי שקלית 0142- שחר",
          1125400,
          "TASE",
          "RF",
          "פנימי",
          "29/03/17",
          15.64,
          "שקל חדש",
          5.5,
          0.03,
          500000,
          138.77,
          693.85,
          0.0,
          2.6,
          1.35
        ],
        [
          "Israel 2.875% 03.16",
          "US46513CXR23",
          "אחר",
          "A+",
          "S&P",
          "30/03/16",
          7.95,
          "דולר אמריקאי",
          2.88,
          3.13,
          65000,
          98.27980553846155,
          230.932973064,
          0.01,
          0.87,
          0.45
        ],
        [
          "Israel 5.125 3/19- ממשל דואלית",
          "US46513E5Y48",
          "אחר",
          "A+",
          "S&P",
          "09/12/14",
          1.92,
          "דולר אמריקאי",
          5.13,
          1.73,
          175000,
          106.67170834285714,
          674.831894904,
          0.01,
          2.53,
          1.31
        ]
      ]
    },
    "אג\"ח קונצרני": {
      "columns": [
        "שם המנפיק/שם נייר ערך",
        "מספר ני\"ע",
        "זירת מסחר",
        "ספק מידע",
        "מספר מנפיק",
        "ענף מסחר",
        "דירוג",
        "שם מדרג",
        "תאריך רכישה",
        "מח\"מ",
        "סוג מטבע",
        "שיעור ריבית",
        "תשואה לפידיון",
        "ערך נקוב",
        "שער",
        "שווי שוק",
        "שעור מערך נקוב מונפק",
        "שעור מנכסי אפיק ההשקעה",
        "שעור מסך נכסי השקעה"
      ],
      "data": [
        [
          "מזרחי טפ הנפק אגח 39- מזרחי טפחות חברה להנפקות בע\"מ",
          2310159,
          "TASE",
          "אחר",
          231,
          "בנקים",
          "AAA",
          "מעלות",
          "02/02/15",
          2.82,
          "שקל חדש",
          0.64,
          0.01,
          500000.0,
          99.05,
          495.25,
          0.02,
          2.2,
          0.96
        ],
        [
          "פועלים הנפקות סדרה 34- הפועלים הנפקות בע\"מ",
          1940576,
          "TASE",
          "אחר",
          194,
          "בנקים",
          "AAA",
          "מעלות",
          "06/05/15",
          3.45,
          "שקל חדש",
          0.7,
          0.01,
          244269.0,
          100.71,
          246.0033099,
          0.01,
          1.09,
          0.48
        ],
        [
          "לאומי התח נד יב- בנק לאומי לישראל בע\"מ",
          6040273,
          "TASE",
          "אחר",
          604,
          "בנקים",
          "AA+",
          "מעלות",
          "",
          0.45,
          "שקל חדש",
          2.6,
          0.0,
          400000.0,
          108.56,
          434.24,
          0.01,
          1.93,
          0.84
        ],
        [
          "מזרחי טפחות הנפק הת 31- מזרחי טפחות חברה להנפקות בע\"מ",
          2310076,
          "TASE",
          "אחר",
          231,
          "בנקים",
          "AA+",
          "מעלות",
          "10/08/15",
          2.39,
          "שקל חדש",
          3.0,
          0.01,
          105000.0,
          113.01,
          118.6605,
          0.02,
          0.53,
          0.23
        ],
        [
          "פועלים הנפ הת י כתה\"נ 10- הפועלים הנפקות בע\"מ",
          1940402,
          "TASE",
          "אחר",
          194,
          "בנקים",
          "AA+",
          "מעלות",
          "14/10/12",
          2.44,
          "שקל חדש",
          4.1,
          0.01,
          540000.0,
          130.18,
          702.972,
          0.02,
          3.13,
          1.36
        ],
        [
          "חשמל אגח 27- חברת החשמל לישראל בע\"מ",
          6000210,
          "TASE",
          "אחר",
          600,
          "חיפושי נפט וגז",
          "AA",
          "מעלות",
          "13/09/16",
          8.74,
          "שקל חדש",
          3.85,
          0.02,
          400000.0,
          114.22,
          456.88,
          0.01,
          2.03,
          0.89
        ],
        [
          "אגוד הנפקות אגח ט- אגוד הנפקות בע\"מ",
          1139492,
          "TASE",
          "אחר",
          1239,
          "בנקים",
          "Aa3",
          "מידרוג",
          "24/11/16",
          4.32,
          "שקל חדש",
          0.95,
          0.83,
          140000.0,
          100.0,
          140.0,
          0.03,
          0.62,
          0.27
        ],
        [
          "גזית גלוב אגח ד- גזית-גלוב בע\"מ",
          1260397,
          "TASE",
          "אחר",
          126,
          "נדל\"ן ובינוי",
          "AA-",
          "מעלות",
          "03/09/15",
          2.96,
          "שקל חדש",
          5.1,
          0.02,
          50000.0,
          129.16,
          64.58,
          0.0,
          0.29,
          0.13
        ],
        [
          "כללביט אגח ג- כללביט מימון בע\"מ",
          1120120,
          "TASE",
          "אחר",
          1324,
          "ביטוח",
          "AA-",
          "מעלות",
          "14/04/16",
          4.03,
          "שקל חדש",
          3.75,
          1.16,
          100000.0,
          118.37,
          118.37,
          0.01,
          0.53,
          0.23
        ],
        [
          "מליסרון אגח יא- מליסרון בע\"מ",
          3230208,
          "TASE",
          "אחר",
          323,
          "נדל\"ן ובינוי",
          "AA-",
          "מעלות",
          "30/01/17",
          6.92,
          "שקל חדש",
          2.3,
          0.02,
          250000.0,
          99.62,
          249.05,
          0.03,
          1.11,
          0.48
        ],
        [
          "פניקס  אגח  2- הפניקס אחזקות בע\"מ",
          7670177,
          "TASE",
          "אחר",
          767,
          "ביטוח",
          "Aa3",
          "מידרוג",
          "06/12/15",
          4.33,
          "שקל חדש",
          2.55,
          0.01,
          266666.66,
          106.05,
          282.79999293,
          0.05,
          1.26,
          0.55
        ],
        [
          "נורסטאר  אגח יא- נורסטאר החזקות אינק  לשעבר גזית אינק",
          7230352,
          "TASE",
          "אחר",
          723,
          "נדל\"ן ובינוי",
          "A+",
          "מעלות",
          "30/08/15",
          5.84,
          "שקל חדש",
          3.0,
          2.98,
          120866.0,
          100.15,
          121.047299,
          0.08,
          0.54,
          0.23
        ],
        [
          "נורסטאר אגח י- נורסטאר החזקות אינק  לשעבר גזית אינק",
          7230345,
          "TASE",
          "אחר",
          723,
          "נדל\"ן ובינוי",
          "A+",
          "מעלות",
          "11/02/16",
          3.74,
          "שקל חדש",
          4.42,
          1.95,
          250000.0,
          109.94,
          274.85,
          0.04,
          1.22,
          0.53
        ],
        [
          "איי.די.או אגח ז- איי.די.או גרופ בע\"מ",
          5050240,
          "TASE",
          "אחר",
          505,
          "נדל\"ן ובינוי",
          "A",
          "מעלות",
          "15/11/16",
          4.35,
          "שקל חדש",
          4.05,
          1.7,
          125000.0,
          110.17,
          137.7125,
          0.02,
          0.61,
          0.27
        ],
        [
          "אלרוב נדלן ד' 3- אלרוב נדל\"ן ומלונאות בע\"מ",
          "IL0038701285",
          "TASE",
          "אחר",
          387,
          "נדל\"ן ובינוי",
          "A2",
          "מידרוג",
          "12/01/17",
          4.72,
          "שקל חדש",
          2.4,
          2.14,
          200000.0,
          101.61,
          203.22,
          0.08,
          0.9,
          0.39
        ],
        [
          "אפריקה מגורים אגח ב- אפריקה ישראל מגורים בע\"מ",
          1126093,
          "TASE",
          "אחר",
          1338,
          "נדל\"ן ובינוי",
          "A2",
          "מידרוג",
          "15/03/16",
          1.72,
          "שקל חדש",
          4.7,
          2.01,
          26138.23,
          106.62,
          27.868580826,
          0.02,
          0.12,
          0.05
        ],
        [
          "דיסקונט שה 1-הפך סחיר 69100950- בנק דיסקונט לישראל בע\"מ",
          6910095,
          "TASE",
          "אחר",
          691,
          "בנקים",
          "A",
          "מעלות",
          "20/10/14",
          4.3,
          "שקל חדש",
          5.1,
          0.02,
          410000.0,
          138.27,
          566.907,
          0.04,
          2.52,
          1.1
        ],
        [
          "חברה לישראל אגח 7- החברה לישראל בע\"מ",
          5760160,
          "TASE",
          "אחר",
          576,
          "השקעות ואחזקות",
          "A",
          "מעלות",
          "09/06/16",
          2.35,
          "שקל חדש",
          4.7,
          0.01,
          160000.0,
          129.57,
          207.312,
          0.01,
          0.92,
          0.4
        ],
        [
          "קרדן רכב אגח ט- קרדן רכב בע\"מ",
          4590162,
          "TASE",
          "אחר",
          459,
          "שירותים",
          "A",
          "מעלות",
          "18/01/16",
          3.07,
          "שקל חדש",
          2.65,
          2.12,
          377419.57,
          100.85,
          380.627636345,
          0.06,
          1.69,
          0.74
        ],
        [
          "שיכון ובינוי אגח 8- שיכון ובינוי - אחזקות בע\"מ",
          1135888,
          "TASE",
          "אחר",
          1068,
          "נדל\"ן ובינוי",
          "A",
          "מעלות",
          "19/01/17",
          6.53,
          "שקל חדש",
          3.65,
          0.03,
          500000.0,
          104.0,
          520.0,
          0.03,
          2.31,
          1.01
        ],
        [
          "אגוד הנפקות סדר COCO- אגוד הנפקות בע\"מ",
          1139153,
          "TASE",
          "אחר",
          1239,
          "בנקים",
          "A-",
          "פנימי",
          "13/09/16",
          4.18,
          "אחר",
          2.85,
          2.2,
          7.0,
          5173000.0,
          362.11,
          0.0,
          1.61,
          0.7
        ],
        [
          "אינטרנט זהב אגח ד- אינטרנט גולד - קווי זהב בע\"מ",
          1131614,
          "TASE",
          "אחר",
          2156,
          "חיפושי נפט וגז",
          "A3",
          "מידרוג",
          "31/12/15",
          3.53,
          "שקל חדש",
          6.0,
          1.71,
          850000.0,
          115.01,
          977.585,
          0.16,
          4.35,
          1.9
        ],
        [
          "דה לסר אגח ג- דה לסר גרופ לימיטד",
          1127299,
          "TASE",
          "אחר",
          1513,
          "נדל\"ן ובינוי",
          "A-",
          "מעלות",
          "02/12/12",
          2.21,
          "שקל חדש",
          5.4,
          2.44,
          29580.0,
          107.17,
          31.700886,
          0.04,
          0.14,
          0.06
        ],
        [
          "דה לסר אגח ד- דה לסר גרופ לימיטד",
          1132059,
          "TASE",
          "אחר",
          1513,
          "נדל\"ן ובינוי",
          "A-",
          "מעלות",
          "10/02/17",
          3.33,
          "שקל חדש",
          2.5,
          4.1,
          250000.0,
          94.95,
          237.375,
          0.08,
          1.06,
          0.46
        ],
        [
          "דיסקונט השקעות אגח ו- חברת השקעות דיסקונט בע\"מ",
          6390207,
          "TASE",
          "אחר",
          639,
          "השקעות ואחזקות",
          "BBB",
          "מעלות",
          "22/09/16",
          4.22,
          "שקל חדש",
          4.95,
          4.14,
          285000.0,
          124.59,
          355.0815,
          0.01,
          1.58,
          0.69
        ],
        [
          "אידיביפת אגח יא- אידיבי חברה לפתוח בע\"מ",
          7980303,
          "TASE",
          "אחר",
          798,
          "השקעות ואחזקות",
          "CCC",
          "מעלות",
          "04/08/16",
          2.52,
          "שקל חדש",
          4.25,
          2.1,
          131584.75,
          105.55,
          138.887703625,
          0.15,
          0.62,
          0.27
        ],
        [
          "כימיקלים לישראל סד ה- כימיקלים לישראל בע\"מ",
          2810299,
          "TASE",
          "אחר",
          281,
          "כימיה, גומי ופלסטיק",
          "AA",
          "מעלות",
          "11/04/16",
          5.17,
          "שקל חדש",
          2.45,
          0.03,
          150000.0,
          99.57,
          149.355,
          0.01,
          0.66,
          0.29
        ],
        [
          "לאומי התחייבות COCO 400- בנק לאומי לישראל בע\"מ",
          6040331,
          "TASE",
          "אחר",
          604,
          "בנקים",
          "AA",
          "מעלות",
          "24/01/16",
          3.6,
          "שקל חדש",
          3.25,
          2.4,
          15.0,
          5157668.0,
          773.6502,
          0.08,
          3.44,
          1.5
        ],
        [
          "מגדל ביטוח ד- מגדל אחזקות ביטוח ופיננסים בע\"מ",
          1137033,
          "TASE",
          "אחר",
          1041,
          "ביטוח",
          "Aa2",
          "מידרוג",
          "15/12/15",
          5.53,
          "שקל חדש",
          1.7,
          2.72,
          650000.0,
          103.7,
          674.05,
          0.09,
          3.0,
          1.31
        ],
        [
          "פניקס הון אגח ד- הפניקס גיוסי הון (2009) בע\"מ",
          1133529,
          "TASE",
          "אחר",
          1527,
          "ביטוח",
          "Aa2",
          "מידרוג",
          "30/11/14",
          6.07,
          "שקל חדש",
          3.85,
          0.03,
          305000.0,
          106.52,
          324.886,
          0.08,
          1.45,
          0.63
        ],
        [
          "בי קום אגח ג- בי קומיוניקיישנס בע\"מ לשעבר סמייל 012",
          1139203,
          "TASE",
          "אחר",
          1422,
          "תקשורת ומדיה",
          "Aa3",
          "מידרוג",
          "20/09/16",
          6.06,
          "שקל חדש",
          3.6,
          3.33,
          850000.0,
          103.71,
          881.535,
          0.04,
          3.92,
          1.71
        ],
        [
          "דה זראסאי אגח ב- דה זראסאי גרופ לטד",
          1131028,
          "TASE",
          "אחר",
          1604,
          "נדל\"ן ובינוי",
          "AA-",
          "מעלות",
          "07/03/16",
          3.59,
          "שקל חדש",
          5.05,
          2.75,
          266650.75,
          109.51,
          292.009236325,
          0.05,
          1.3,
          0.57
        ],
        [
          "וורטון פרופרטיז אגח א",
          1140169,
          "TASE",
          "אחר",
          0,
          "אחר",
          "AA-",
          "מעלות",
          "01/03/17",
          4.43,
          "שקל חדש",
          3.9,
          3.78,
          500000.0,
          101.15,
          505.75,
          0.06,
          2.25,
          0.98
        ],
        [
          "מויניאן אגח א- מויניאן לימיטד",
          1135656,
          "TASE",
          "אחר",
          1643,
          "נדל\"ן ובינוי",
          "Aa3",
          "מידרוג",
          "06/03/16",
          3.36,
          "שקל חדש",
          4.2,
          3.61,
          250000.0,
          103.15,
          257.875,
          0.02,
          1.15,
          0.5
        ],
        [
          "פניקס הון אגח ח- הפניקס גיוסי הון (2009) בע\"מ",
          1139815,
          "TASE",
          "אחר",
          1527,
          "ביטוח",
          "Aa3",
          "מידרוג",
          "15/01/17",
          7.23,
          "שקל חדש",
          3.61,
          3.35,
          75000.0,
          102.89,
          77.1675,
          0.02,
          0.34,
          0.15
        ],
        [
          "קיי.בי.אס הולדינג אגח א- קיי.בי.אס.אס.או.אר(בי.וי.איי)הולדינג אל.טי.די",
          1137918,
          "TASE",
          "אחר",
          1662,
          "נדל\"ן ובינוי",
          "AA-",
          "מעלות",
          "21/12/16",
          3.61,
          "שקל חדש",
          4.25,
          3.76,
          500000.0,
          102.26,
          511.3,
          0.05,
          2.27,
          0.99
        ],
        [
          "דיסקונט התחי נד- בנק דיסקונט לישראל בע\"מ",
          6910160,
          "TASE",
          "אחר",
          691,
          "בנקים",
          "A+",
          "מעלות",
          "11/01/17",
          4.45,
          "שקל חדש",
          3.6,
          0.03,
          10.0,
          5170125.0,
          517.0125,
          0.06,
          2.3,
          1.0
        ],
        [
          "נמקו אגח א'",
          1139575,
          "TASE",
          "אחר",
          0,
          "נדל\"ן ובינוי",
          "A+",
          "מעלות",
          "01/02/17",
          3.99,
          "שקל חדש",
          5.8,
          0.05,
          500000.0,
          104.68,
          523.4,
          0.11,
          2.33,
          1.02
        ],
        [
          "קורנרסטון א- CORNERSTONE CLO",
          1139732,
          "TASE",
          "אחר",
          10099,
          "נדל\"ן ובינוי",
          "A1",
          "מידרוג",
          "27/12/16",
          4.13,
          "שקל חדש",
          4.9,
          4.26,
          170000.0,
          104.11,
          176.987,
          0.06,
          0.79,
          0.34
        ],
        [
          "רילייטד א' 2020- רילייטד פרוטפוליו מסחרי לימיטד",
          1134923,
          "TASE",
          "אחר",
          1638,
          "נדל\"ן ובינוי",
          "A+",
          "מעלות",
          "18/06/15",
          3.04,
          "שקל חדש",
          4.0,
          3.39,
          350000.0,
          105.31,
          368.585,
          0.04,
          1.64,
          0.72
        ],
        [
          "אפריקה ישראל ג- אפריקה ישראל מגורים בע\"מ",
          1135698,
          "TASE",
          "אחר",
          1338,
          "נדל\"ן ובינוי",
          "A2",
          "מידרוג",
          "25/08/16",
          3.64,
          "שקל חדש",
          3.9,
          0.03,
          380000.0,
          104.27,
          396.226,
          0.16,
          1.76,
          0.77
        ],
        [
          "דלק קבוצה  לג- קבוצת דלק בע\"מ",
          1138882,
          "TASE",
          "אחר",
          1095,
          "השקעות ואחזקות",
          "A",
          "מעלות",
          "31/07/16",
          4.48,
          "שקל חדש",
          2.8,
          2.8,
          350000.0,
          100.7,
          352.45,
          0.05,
          1.57,
          0.68
        ],
        [
          "חברה לישראל אגח 9- החברה לישראל בע\"מ",
          5760202,
          "TASE",
          "אחר",
          576,
          "השקעות ואחזקות",
          "A",
          "מעלות",
          "04/09/12",
          0.74,
          "שקל חדש",
          6.0,
          0.01,
          158333.37,
          105.6,
          167.20003872,
          0.07,
          0.74,
          0.32
        ],
        [
          "ספנסר אגח א- ספנסר אקוויטי גרופ לימיטד",
          1133800,
          "TASE",
          "אחר",
          1628,
          "נדל\"ן ובינוי",
          "A",
          "מעלות",
          "29/01/17",
          3.24,
          "שקל חדש",
          6.9,
          0.04,
          300000.0,
          112.32,
          336.96,
          0.05,
          1.5,
          0.65
        ],
        [
          "קופרליין אגח א- קופרליין אמריקאס לימיטד",
          1136589,
          "TASE",
          "אחר",
          1648,
          "נדל\"ן ובינוי",
          "A",
          "מעלות",
          "09/03/16",
          2.0,
          "שקל חדש",
          6.0,
          3.02,
          273534.8,
          108.86,
          297.76998328,
          0.1,
          1.32,
          0.58
        ],
        [
          "כנפיים אחזקות אגח ז- כנפיים אחזקות בע\"מ",
          5430137,
          "TASE",
          "אחר",
          543,
          "שירותים",
          "A-",
          "מעלות",
          "06/09/16",
          3.63,
          "שקל חדש",
          6.25,
          3.06,
          477108.0,
          111.8,
          533.406744,
          0.34,
          2.37,
          1.04
        ],
        [
          "נאוי אגח ב- קבוצת האחים נאוי בע\"מ לשעבר גולדן אקוויטי",
          2080166,
          "TASE",
          "אחר",
          208,
          "שירותים פיננסיים",
          "A-",
          "מעלות",
          "18/02/16",
          1.39,
          "שקל חדש",
          2.7,
          1.4,
          333350.0,
          102.06,
          340.21701,
          0.1,
          1.51,
          0.66
        ],
        [
          "אלדן תחבורה  א- אלדן בע\"מ",
          1134840,
          "TASE",
          "אחר",
          10503,
          "שירותים",
          "Baa1",
          "מידרוג",
          "10/11/15",
          2.07,
          "שקל חדש",
          4.3,
          0.03,
          145453.99,
          102.65,
          149.308520735,
          0.03,
          0.66,
          0.29
        ],
        [
          "אלדן תחבורה  ב- אלדן בע\"מ",
          1138254,
          "TASE",
          "אחר",
          10503,
          "שירותים",
          "Baa1",
          "מידרוג",
          "02/11/16",
          2.49,
          "שקל חדש",
          4.25,
          0.04,
          150000.0,
          102.98,
          154.47,
          0.02,
          0.69,
          0.3
        ],
        [
          "אלון רבוע כחול אגח ד'- אלון החזקות ברבוע כחול- ישראל בע\"מ לשעבר רבוע כחול",
          1139583,
          "TASE",
          "אחר",
          2063,
          "מסחר",
          "Baa1",
          "מידרוג",
          "12/12/16",
          4.83,
          "שקל חדש",
          4.6,
          3.65,
          150000.0,
          106.25,
          159.375,
          0.02,
          0.71,
          0.31
        ],
        [
          "בזן אגח ד- בתי זקוק לנפט בע\"מ",
          2590362,
          "TASE",
          "אחר",
          259,
          "חיפושי נפט וגז",
          "BBB+",
          "מעלות",
          "23/10/14",
          2.75,
          "שקל חדש",
          6.0,
          2.45,
          481500.0,
          111.6,
          537.354,
          0.08,
          2.39,
          1.04
        ],
        [
          "בזן אגח ה- בתי זקוק לנפט בע\"מ",
          2590388,
          "TASE",
          "אחר",
          259,
          "חיפושי נפט וגז",
          "BBB+",
          "מעלות",
          "20/08/15",
          4.8,
          "שקל חדש",
          5.9,
          0.03,
          200000.0,
          114.39,
          228.78,
          0.03,
          1.02,
          0.44
        ],
        [
          "ברוקלנד אפריל אגח ב- ברוקלנד אפריל לימיטד",
          1136993,
          "TASE",
          "אחר",
          1617,
          "נדל\"ן ובינוי",
          "BBB+",
          "מעלות",
          "08/12/15",
          3.14,
          "שקל חדש",
          8.85,
          6.76,
          100000.0,
          110.0,
          110.0,
          0.14,
          0.49,
          0.21
        ],
        [
          "אידיבי פיתוח אגח יב- אידיבי חברה לפתוח בע\"מ",
          7980311,
          "TASE",
          "אחר",
          798,
          "השקעות ואחזקות",
          "CCC",
          "מעלות",
          "30/11/16",
          2.44,
          "שקל חדש",
          6.95,
          4.14,
          500000.0,
          107.85,
          539.25,
          0.13,
          2.4,
          1.05
        ],
        [
          "אידיבי פתוח יג'- אידיבי חברה לפתוח בע\"מ",
          7980329,
          "TASE",
          "אחר",
          798,
          "השקעות ואחזקות",
          "CCC",
          "מעלות",
          "23/02/17",
          2.48,
          "שקל חדש",
          5.4,
          4.63,
          950000.0,
          102.77,
          976.315,
          0.09,
          4.34,
          1.9
        ],
        [
          "גאון אחז  אגח ב- ב.גאון אחזקות בע\"מ",
          1133727,
          "TASE",
          "אחר",
          1452,
          "השקעות ואחזקות",
          0,
          "לא מדורג",
          "17/11/14",
          1.58,
          "שקל חדש",
          6.8,
          2.4,
          145000.0,
          109.4,
          158.63,
          0.16,
          0.71,
          0.31
        ],
        [
          "רציו מימון אגח ב- רציו חיפושי נפט (מימון) בע\"מ",
          1139443,
          "TASE",
          "אחר",
          1625,
          "חיפושי נפט וגז",
          0,
          "לא מדורג",
          "14/11/16",
          5.08,
          "שקל חדש",
          2.0,
          4.86,
          450000.0,
          113.5,
          510.75,
          0.07,
          2.27,
          0.99
        ],
        [
          "אבנר אגח א- אבנר חיפושי נפט וגז - שותפות מוגבלת",
          2680130,
          "TASE",
          "אחר",
          268,
          "חיפושי נפט וגז",
          "A1",
          "מידרוג",
          "29/12/16",
          4.29,
          "שקל חדש",
          4.5,
          3.61,
          250000.0,
          99.96,
          249.9,
          0.03,
          1.11,
          0.49
        ],
        [
          "חברה לישראל אג\"ח 11- החברה לישראל בע\"מ",
          5760244,
          "TASE",
          "אחר",
          576,
          "השקעות ואחזקות",
          "A",
          "מעלות",
          "08/01/17",
          4.54,
          "שקל חדש",
          5.0,
          0.04,
          1050000.0,
          99.43,
          1044.015,
          0.08,
          4.64,
          2.03
        ],
        [
          "בזן אגח ו- בתי זקוק לנפט בע\"מ",
          2590396,
          "TASE",
          "אחר",
          259,
          "חיפושי נפט וגז",
          "BBB+",
          "מעלות",
          "21/04/16",
          4.37,
          "שקל חדש",
          6.7,
          0.04,
          250000.0,
          105.1,
          262.75,
          0.02,
          1.17,
          0.51
        ],
        [
          "חלל תקש אגח טז- חלל-תקשורת בע\"מ",
          1139922,
          "TASE",
          "אחר",
          1132,
          "חיפושי נפט וגז",
          0,
          "לא מדורג",
          "24/01/17",
          5.7,
          "שקל חדש",
          5.95,
          4.77,
          400000.0,
          102.94,
          411.76,
          0.04,
          1.83,
          0.8
        ],
        [
          "devtam 3.839% 30/12/2018- דלק ואבנר תמר בונד בע\"מ",
          "il0011321580",
          "אחר",
          "בלומברג",
          1620,
          "Energy",
          "AA",
          "מעלות",
          "12/08/15",
          1.7,
          "דולר אמריקאי",
          3.84,
          2.77,
          140000.0,
          102.796,
          520.250556,
          0.04,
          2.31,
          1.01
        ],
        [
          "Israel elec7.25% 01/2019- חברת החשמל לישראל בע\"מ",
          "us46507naa81",
          "אחר",
          "בלומברג",
          600,
          "Utilities",
          "BB+",
          "S&P",
          "08/10/15",
          1.7,
          "דולר אמריקאי",
          7.25,
          2.44,
          40000.0,
          109.858139,
          158.854868994,
          0.0,
          0.71,
          0.31
        ]
      ]
    },
    "תעודות סל": {
      "columns": [
        "שם המנפיק/שם נייר ערך",
        "מספר ני\"ע",
        "זירת מסחר",
        "מספר מנפיק",
        "ענף מסחר",
        "סוג מטבע",
        "ערך נקוב",
        "שער",
        "שווי שוק",
        "שעור מערך נקוב מונפק",
        "שעור מנכסי אפיק ההשקעה",
        "שעור מסך נכסי השקעה"
      ],
      "data": [
        [
          "פס.תלבונד תשואות",
          1138080,
          "TASE",
          1446,
          "שירותים פיננסיים",
          "שקל חדש",
          3000,
          3472.7,
          104.181,
          0.02,
          21.83,
          0.2
        ],
        [
          "פסגות ברקליס חמש",
          1138072,
          "TASE",
          1446,
          "שירותים פיננסיים",
          "שקל חדש",
          5000,
          7461.5,
          373.075,
          0.07,
          78.17,
          0.72
        ]
      ]
    },
    "לא סחיר - אג\"ח קונצרני": {
      "columns": [
        "שם המנפיק/שם נייר ערך",
        "מספר ני\"ע",
        "ספק המידע",
        "מספר מנפיק",
        "ענף מסחר",
        "דירוג",
        "שם מדרג",
        "תאריך רכישה",
        "מח\"מ",
        "סוג מטבע",
        "שיעור ריבית",
        "תשואה לפידיון",
        "ערך נקוב",
        "שער",
        "שווי הוגן",
        "שעור מערך נקוב מונפק",
        "שעור מנכסי אפיק ההשקעה",
        "שעור מסך נכסי השקעה"
      ],
      "data": [
        [
          "ביטוח ישיר אגח יא- ביטוח ישיר - השקעות פיננסיות בע\"מ",
          1138825,
          "אחר",
          1089,
          "השקעות ואחזקות",
          "A2",
          "מידרוג",
          "28/07/16",
          5.8,
          "שקל חדש",
          4.6,
          0.04,
          550000,
          106.44,
          585.42,
          0.08,
          39.77,
          1.14
        ],
        [
          "אמקור אגח א לס רמ- אמפא השקעות בע\"מ",
          1133545,
          "אחר",
          703,
          "שירותים",
          "A3",
          "מידרוג",
          "23/09/14",
          2.42,
          "שקל חדש",
          5.15,
          3.5,
          142856,
          107.64,
          153.7701984,
          0.12,
          10.45,
          0.3
        ],
        [
          "דלק (תמר) 2018_$ - רמ- דלק ואבנר תמר בונד בע\"מ",
          1132158,
          "אחר",
          1620,
          "חיפושי נפט וגז",
          "AA",
          "מעלות",
          "12/05/14",
          1.7,
          "דולר אמריקאי",
          3.84,
          2.99,
          72056,
          102.41,
          266.760066804,
          0.02,
          18.12,
          0.52
        ],
        [
          "אורמת  סדרה 2 12.09.2016- אורמת טכנולגיות אינק דואלי",
          1139161,
          "אחר",
          2250,
          "קלינטק",
          "A+",
          "מעלות",
          "14/09/16",
          3.28,
          "דולר אמריקאי",
          3.7,
          4.04,
          130000,
          99.18,
          466.09641,
          0.19,
          31.66,
          0.9
        ]
      ]
    },
    "לא סחיר - מוצרים מובנים": {
      "columns": [
        "שם המנפיק/שם נייר ערך",
        "מספר ני\"ע",
        "נכס הבסיס",
        "דירוג",
        "שם מדרג",
        "תאריך רכישה",
        "מח\"מ",
        "סוג מטבע",
        "שיעור ריבית",
        "תשואה לפידיון",
        "ערך נקוב",
        "שער",
        "שווי הוגן",
        "שעור מערך נקוב מונפק",
        "שעור מנכסי אפיק ההשקעה",
        "שעור מסך נכסי השקעה"
      ],
      "data": [
        [
          "מימון ישיר סידרה 2- מימון ישיר הנפקות  בע\"מ",
          1136035,
          "אשראי",
          "AAA",
          "מעלות",
          "12/08/15",
          1.34,
          "שקל חדש",
          1.95,
          1.42,
          248049.93,
          100.81,
          250.059134433,
          0,
          100,
          0.49
        ]
      ]
    },
    "השקעות אחרות ": {
      "columns": [
        "שם המנפיק/שם נייר ערך",
        "מספר הנייר",
        "דירוג",
        "שם המדרג",
        "שעור הריבית",
        "סוג מטבע",
        "תשואה לפדיון",
        "שווי הוגן",
        "שעור מנכסי אפיק ההשקעה",
        "שעור מסך נכסי השקעה"
      ],
      "data": [
        [
          "זכאים מס עמיתים",
          28200000,
          0,
          "לא מדורג",
          0,
          "שקל חדש",
          0,
          -0.00055,
          0.0,
          0.0
        ],
        [
          "חו\"ז חברה מנהלת*",
          28080000,
          0,
          "לא מדורג",
          0,
          "שקל חדש",
          0,
          -23.26141,
          -23.46,
          -0.05
        ],
        [
          "ממשלתי שקלי 324(ריבית לקבל)",
          1130848,
          0,
          "פנימי",
          0,
          "שקל חדש",
          0,
          7.5,
          7.56,
          0.01
        ],
        [
          "מגדל ביטוח ד(ריבית לקבל)",
          1137033,
          0,
          "מידרוג",
          0,
          "שקל חדש",
          0,
          28.73605,
          28.98,
          0.06
        ],
        [
          "דיסקונט שה 1-הפך סחיר 69100950(ריבית לקבל)",
          6910095,
          0,
          "מעלות",
          0,
          "שקל חדש",
          0,
          6.22783,
          6.28,
          0.01
        ],
        [
          "לאומי התחייבות COCO 400(ריבית לקבל)",
          6040331,
          0,
          "מעלות",
          0,
          "שקל חדש",
          0,
          6.09375,
          6.14,
          0.01
        ],
        [
          "אפריקה ישראל ג(פדיון לקבל)",
          1135698,
          0,
          "מידרוג",
          0,
          "שקל חדש",
          0,
          20.0,
          20.17,
          0.04
        ],
        [
          "אפריקה ישראל ג(ריבית לקבל)",
          1135698,
          0,
          "מידרוג",
          0,
          "שקל חדש",
          0,
          7.8,
          7.86,
          0.02
        ],
        [
          "אפריקה מגורים אגח ב(פדיון לקבל)",
          1126093,
          0,
          "מידרוג",
          0,
          "שקל חדש",
          0,
          11.0146,
          11.11,
          0.02
        ],
        [
          "אפריקה מגורים אגח ב(ריבית לקבל)",
          1126093,
          0,
          "מידרוג",
          0,
          "שקל חדש",
          0,
          0.88438,
          0.89,
          0.0
        ],
        [
          "גזית גלוב אגח ד(ריבית לקבל)",
          1260397,
          0,
          "מעלות",
          0,
          "שקל חדש",
          0,
          2.98574,
          3.01,
          0.01
        ],
        [
          "נורסטאר  אגח יא(ריבית לקבל)",
          7230352,
          0,
          "מעלות",
          0,
          "שקל חדש",
          0,
          1.81299,
          1.83,
          0.0
        ],
        [
          "נורסטאר אגח י(ריבית לקבל)",
          7230345,
          0,
          "מעלות",
          0,
          "שקל חדש",
          0,
          5.54573,
          5.59,
          0.01
        ],
        [
          "רילייטד א' 2020(ריבית לקבל)",
          1134923,
          0,
          "מעלות",
          0,
          "שקל חדש",
          0,
          8.925,
          9.0,
          0.02
        ],
        [
          "כנפיים אחזקות אגח ז(ריבית לקבל)",
          5430137,
          0,
          "מעלות",
          0,
          "שקל חדש",
          0,
          14.90963,
          15.03,
          0.03
        ]
      ]
    }
  }
}